LICENSE.md
MANIFEST.in
README.md
setup.cfg
setup.py
mae/404.html
mae/__init__.py
mae/base.html
mae/content.html
mae/keyboard-modal.html
mae/maeguias_theme.yml
mae/main.html
mae/nav-sub.html
mae/nav.html
mae/search-modal.html
mae/toc.html
mae/css/base.css
mae/css/base.min.css
mae/css/bootstrap-custom.css
mae/css/bootstrap-custom.min.css
mae/css/highlight.css
mae/css/highlight.min.css
mae/css/mae.css
mae/css/mae.min.css
mae/fonts/fontawesome-webfont.eot
mae/fonts/fontawesome-webfont.svg
mae/fonts/fontawesome-webfont.ttf
mae/fonts/fontawesome-webfont.woff
mae/img/favicon.ico
mae/img/grid1.png
mae/img/grid10.png
mae/img/grid11.png
mae/img/grid12.png
mae/img/grid13.png
mae/img/grid14.png
mae/img/grid15.png
mae/img/grid16.png
mae/img/grid17.png
mae/img/grid18.png
mae/img/grid19.png
mae/img/grid2.png
mae/img/grid20.png
mae/img/grid3.png
mae/img/grid4.png
mae/img/grid5.png
mae/img/grid6.png
mae/img/grid7.png
mae/img/grid8.png
mae/img/grid9.png
mae/js/base.js
mae/js/bootstrap-3.0.3.min.js
mae/js/highlight.pack.js
maetema.egg-info/PKG-INFO
maetema.egg-info/SOURCES.txt
maetema.egg-info/dependency_links.txt
maetema.egg-info/entry_points.txt
maetema.egg-info/not-zip-safe
maetema.egg-info/top_level.txt