Metadata-Version: 1.0
Name: maetema
Version: 1.1.5
Summary: Tema de MaeDocs
Home-page: https://docs.maeorg.site
Author: Ham Won Trikru
Author-email: lwonderlich@gmail.com
License: MIT
Platform: UNKNOWN
